pba_waeber2013.py
pba_waeber2013-0.1.0.dist-info/LICENSE.txt
pba_waeber2013-0.1.0.dist-info/WHEEL
pba_waeber2013-0.1.0.dist-info/METADATA
pba_waeber2013-0.1.0.dist-info/RECORD
