Metadata-Version: 2.1
Name: pba_waeber2013
Version: 0.1.0
Summary: Implementation of the stochastic root-finding algorithm described by 
Home-page: https://github.com/kalekundert/pba_waeber2013
Author: Kale Kundert
Author-email: kale@thekunderts.net
Requires-Python: ~=3.7
Classifier: Programming Language :: Python :: 3
Classifier: License :: OSI Approved :: MIT License
Requires-Dist: numpy
Requires-Dist: sphinx ; extra == "doc"
Requires-Dist: sphinx_rtd_theme ; extra == "doc"
Requires-Dist: autoclasstoc ; extra == "doc"
Requires-Dist: pytest ; extra == "test"
Requires-Dist: pytest-cov ; extra == "test"
Requires-Dist: parametrize_from_file ; extra == "test"
Requires-Dist: coveralls ; extra == "test"
Project-URL: Bug Tracker, https://github.com/kalekundert/pba_waeber2013/issues
Project-URL: Continuous Integration, https://github.com/kalekundert/pba_waeber2013/actions
Project-URL: Documentation, https://pba_waeber2013.readthedocs.io/en/latest/
Project-URL: Test Coverage, https://coveralls.io/github/kalekundert/pba_waeber2013
Project-URL: Version Control, https://github.com/kalekundert/pba_waeber2013
Provides-Extra: doc
Provides-Extra: test
